giturlparse/__init__.py
giturlparse/parser.py
giturlparse/result.py
giturlparse/platforms/__init__.py
giturlparse/platforms/assembla.py
giturlparse/platforms/base.py
giturlparse/platforms/bitbucket.py
giturlparse/platforms/friendcode.py
giturlparse/platforms/github.py
giturlparse/platforms/gitlab.py
giturlparse/tests/__init__.py
giturlparse/tests/test_parse.py
giturlparse/tests/test_rewrite.py
giturlparse2-1.0.0.dist-info/LICENSE
giturlparse2-1.0.0.dist-info/METADATA
giturlparse2-1.0.0.dist-info/WHEEL
giturlparse2-1.0.0.dist-info/top_level.txt
giturlparse2-1.0.0.dist-info/RECORD
