Metadata-Version: 2.1
Name: giturlparse2
Version: 1.0.0
Summary: A Git URL parsing module (supports parsing and rewriting)
Home-page: https://github.com/godfryd/giturlparse2
Author: Aaron O Mullan
Author-email: aaron@friendco.de
Maintainer: Michal Nowikowski
Maintainer-email: godfryd@gmail.com
License: Apache v2
Keywords: giturlparse
Classifier: Development Status :: 5 - Production/Stable
Classifier: Framework :: Django
Classifier: Intended Audience :: Developers
Classifier: License :: OSI Approved :: Apache Software License
Classifier: Natural Language :: English
Classifier: Programming Language :: Python :: 3.8
Classifier: Programming Language :: Python :: 3.9
Classifier: Programming Language :: Python :: 3.10
Classifier: Programming Language :: Python :: 3.11
Requires-Python: >=3.8
License-File: LICENSE
